{
    "DNDConfig": null,
    "_height_": {
        "type": "string",
        "value": "60%"
    },
    "_left_": {
        "type": "string",
        "value": "0"
    },
    "_margin_": [
        0,
        0,
        0,
        0
    ],
    "_orientation_": 6,
    "_padding_": [
        0,
        0,
        0,
        0
    ],
    "_percent_": true,
    "_skin_": "sc8db981b4544c9b8c8fa9a9ab61cda2",
    "_top_": {
        "type": "string",
        "value": "20%"
    },
    "_width_": {
        "type": "string",
        "value": "100%"
    },
    "allboxes": [],
    "autogrowmode": 0,
    "canUpdateUI": true,
    "children": [
        "lblEnterString",
        "tbxCommandInput",
        "btnSubmitString"
    ],
    "clipbounds": true,
    "containerweight": 100,
    "enablescrolling": true,
    "id": "flxContent",
    "info": null,
    "iscustomlayout": false,
    "isvisible": true,
    "kuid": "a23f7bb02420497282e552392bb92af9",
    "layouttype": 4,
    "name": "kony.ui.FlexContainer",
    "parent": "flxMainContainer",
    "pf": "frmLandingScreen",
    "retaincontentalignment": false,
    "retainflexpositionproperties": false,
    "retainflowhorizontalalignment": false,
    "snapgridsize": 10,
    "snaptogrid": true,
    "wType": "FlexContainer",
    "widgetalignment": 1
}